{"candidate":"{\"prop\":\"candidate\",\"candidate_information\":[{\"candidate\":\"candidate:3351850224 1 udp 2113937151 192.168.0.5 60394 typ host generation 0 ufrag QU18 network-cost 999\",\"sdpMid\":\"0\",\"sdpMLineIndex\":0},{\"candidate\":\"candidate:3351850224 1 udp 2113937151 192.168.0.5 45988 typ host generation 0 ufrag QU18 network-cost 999\",\"sdpMid\":\"1\",\"sdpMLineIndex\":1},{\"candidate\":\"candidate:842163049 1 udp 1677729535 49.205.49.197 60394 typ srflx raddr 192.168.0.5 rport 60394 generation 0 ufrag QU18 network-cost 999\",\"sdpMid\":\"0\",\"sdpMLineIndex\":0},{\"candidate\":\"candidate:842163049 1 udp 1677729535 49.205.49.197 45988 typ srflx raddr 192.168.0.5 rport 45988 generation 0 ufrag QU18 network-cost 999\",\"sdpMid\":\"1\",\"sdpMLineIndex\":1}],\"target_id\":\"nila\"}"}